{
  "db_name": "PostgreSQL",
  "query": "\n        SELECT bm.board_id, bm.user_id, bm.role, bm.created_at,\n               u.username, u.email, u.profile_picture_url\n        FROM board_members bm\n        JOIN users u ON u.id = bm.user_id\n        WHERE bm.board_id = $1\n        ORDER BY bm.created_at ASC\n        ",
  "describe": {
    "columns": [
      {
        "ordinal": 0,
        "name": "board_id",
        "type_info": "Uuid"
      },
      {
        "ordinal": 1,
        "name": "user_id",
        "type_info": "Uuid"
      },
      {
        "ordinal": 2,
        "name": "role",
        "type_info": "Text"
      },
      {
        "ordinal": 3,
        "name": "created_at",
        "type_info": "Timestamptz"
      },
      {
        "ordinal": 4,
        "name": "username",
        "type_info": "Varchar"
      },
      {
        "ordinal": 5,
        "name": "email",
        "type_info": "Varchar"
      },
      {
        "ordinal": 6,
        "name": "profile_picture_url",
        "type_info": "Text"
      }
    ],
    "parameters": {
      "Left": [
        "Uuid"
      ]
    },
    "nullable": [
      false,
      false,
      false,
      false,
      false,
      false,
      true
    ]
  },
  "hash": "e6197913d3259ecc49421174a3ec671738ce96cf95b42ad9c1752f754432269b"
}
