{
  "db_name": "PostgreSQL",
  "query": "\n        INSERT INTO board_snapshots (board_id, seq, state)\n        VALUES ($1, $2, $3)\n        RETURNING id, board_id, seq, state, created_at\n        ",
  "describe": {
    "columns": [
      {
        "ordinal": 0,
        "name": "id",
        "type_info": "Uuid"
      },
      {
        "ordinal": 1,
        "name": "board_id",
        "type_info": "Uuid"
      },
      {
        "ordinal": 2,
        "name": "seq",
        "type_info": "Int8"
      },
      {
        "ordinal": 3,
        "name": "state",
        "type_info": "Jsonb"
      },
      {
        "ordinal": 4,
        "name": "created_at",
        "type_info": "Timestamptz"
      }
    ],
    "parameters": {
      "Left": [
        "Uuid",
        "Int8",
        "Jsonb"
      ]
    },
    "nullable": [
      false,
      false,
      false,
      false,
      false
    ]
  },
  "hash": "5f931035234ccaea3054306c94510b53831d3f7a0e6f0474c4d69b0abf02c275"
}
